simpleperf/__init__.py
simpleperf-0.0.1.dist-info/LICENSE
simpleperf-0.0.1.dist-info/METADATA
simpleperf-0.0.1.dist-info/WHEEL
simpleperf-0.0.1.dist-info/top_level.txt
simpleperf-0.0.1.dist-info/RECORD
