Metadata-Version: 2.1
Name: simpleperf
Version: 0.0.1
Summary: Simpleperf is a native CPU profiling tool for Android.
Home-page: https://github.com/shizhao-git/simpleperf
Author: shizhao
Author-email: shizhao@mail.nwpu.edu.cn
License: UNKNOWN
Platform: UNKNOWN
License-File: LICENSE
